hvoFuncs/__init__.py
hvoFuncs/data_exporter.py
hvoFuncs/misc.py
hvoFuncs/sharepoint.py
hvoFuncs/vars.py
hvoFuncs-0.1.9.dist-info/LICENSE
hvoFuncs-0.1.9.dist-info/METADATA
hvoFuncs-0.1.9.dist-info/WHEEL
hvoFuncs-0.1.9.dist-info/top_level.txt
hvoFuncs-0.1.9.dist-info/RECORD
