Metadata-Version: 2.1
Name: hvoFuncs
Version: 0.1.9
Summary: Common functions for dataframe manipulation and for using certain applications
Home-page: UNKNOWN
Author: Harrison Van Oort
Author-email: harroort@amazon.com
License: UNKNOWN
Platform: UNKNOWN
Classifier: Programming Language :: Python :: 3
Classifier: License :: OSI Approved :: MIT License
Classifier: Operating System :: OS Independent
Requires-Python: >=3.6
Requires-Dist: pandas (==0.25.3)
Requires-Dist: requests (==2.22.0)
Requires-Dist: requests-ntlm (==1.1.0)
Requires-Dist: s3fs (==0.4.0)
